nnetsauce/__init__.py
nnetsauce/attention/__init__.py
nnetsauce/attention/attention.py
nnetsauce/base/__init__.py
nnetsauce/base/base.py
nnetsauce/base/baseRegressor.py
nnetsauce/boosting/__init__.py
nnetsauce/boosting/adaBoostClassifier.py
nnetsauce/boosting/bst.py
nnetsauce/custom/__init__.py
nnetsauce/custom/custom.py
nnetsauce/custom/customBackpropRegressor.py
nnetsauce/custom/customClassifier.py
nnetsauce/custom/customRegressor.py
nnetsauce/datasets/__init__.py
nnetsauce/datasets/dowload.py
nnetsauce/deep/__init__.py
nnetsauce/deep/deepClassifier.py
nnetsauce/deep/deepMTS.py
nnetsauce/deep/deepRegressor.py
nnetsauce/glm/__init__.py
nnetsauce/glm/glm.py
nnetsauce/glm/glmClassifier.py
nnetsauce/glm/glmRegressor.py
nnetsauce/kernel/__init__.py
nnetsauce/kernel/kernel.py
nnetsauce/lazypredict/__init__.py
nnetsauce/lazypredict/config.py
nnetsauce/lazypredict/lazydeepClassifier.py
nnetsauce/lazypredict/lazydeepMTS.py
nnetsauce/lazypredict/lazydeepRegressor.py
nnetsauce/mts/__init__.py
nnetsauce/mts/classical.py
nnetsauce/mts/mlarch.py
nnetsauce/mts/mts.py
nnetsauce/mts/multioutputmts.py
nnetsauce/mts/stackedmts.py
nnetsauce/multitask/__init__.py
nnetsauce/multitask/multitaskClassifier.py
nnetsauce/multitask/simplemultitaskClassifier.py
nnetsauce/neuralnet/__init__.py
nnetsauce/neuralnet/neuralnetclassification.py
nnetsauce/neuralnet/neuralnetregression.py
nnetsauce/nonconformist/__init__.py
nnetsauce/nonconformist/acp.py
nnetsauce/nonconformist/base.py
nnetsauce/nonconformist/cp.py
nnetsauce/nonconformist/evaluation.py
nnetsauce/nonconformist/icp.py
nnetsauce/nonconformist/nc.py
nnetsauce/nonconformist/util.py
nnetsauce/optimizers/__init__.py
nnetsauce/optimizers/helpers.py
nnetsauce/optimizers/optimizer.py
nnetsauce/predictioninterval/__init__.py
nnetsauce/predictioninterval/predictioninterval.py
nnetsauce/predictionset/__init__.py
nnetsauce/predictionset/predictionset.py
nnetsauce/quantile/__init__.py
nnetsauce/quantile/quantileclassification.py
nnetsauce-0.48.0.dist-info/licenses/LICENSE
nnetsauce-0.48.0.dist-info/METADATA
nnetsauce-0.48.0.dist-info/WHEEL
nnetsauce-0.48.0.dist-info/top_level.txt
nnetsauce-0.48.0.dist-info/RECORD
