Metadata-Version: 2.4
Name: nnetsauce
Version: 0.48.0
Summary: Quasi-randomized (neural) networks
Home-page: https://techtonique.github.io/nnetsauce/
Download-URL: https://github.com/Techtonique/nnetsauce
Author: T. Moudiki
Author-email: thierry.moudiki@gmail.com
License: BSD Clause Clear
Classifier: Development Status :: 3 - Alpha
Classifier: Intended Audience :: Developers
Classifier: Programming Language :: Python :: 3
License-File: LICENSE
Requires-Dist: jax
Requires-Dist: joblib
Requires-Dist: matplotlib
Requires-Dist: numpy
Requires-Dist: optax
Requires-Dist: pandas
Requires-Dist: requests
Requires-Dist: scipy
Requires-Dist: scikit-learn
Requires-Dist: statsmodels
Requires-Dist: threadpoolctl
Requires-Dist: tqdm
Dynamic: author
Dynamic: author-email
Dynamic: classifier
Dynamic: description
Dynamic: download-url
Dynamic: home-page
Dynamic: keywords
Dynamic: license
Dynamic: license-file
Dynamic: requires-dist
Dynamic: summary
